stringth/__init__.py
stringth/funcs.py
stringth-0.0.4.dist-info/LICENSE_APACHE
stringth-0.0.4.dist-info/METADATA
stringth-0.0.4.dist-info/WHEEL
stringth-0.0.4.dist-info/top_level.txt
stringth-0.0.4.dist-info/RECORD
