Metadata-Version: 2.1
Name: stringth
Version: 0.0.4
Summary: Conversion functions between numbers and strings
Home-page: UNKNOWN
Author: taennan
Author-email: taennan@scoobyapps.com
License: Apache-2.0
Keywords: string,str,nth
Platform: UNKNOWN
Classifier: Topic :: Utilities
Classifier: Intended Audience :: Developers
Classifier: Natural Language :: English
Classifier: Programming Language :: Python :: 3
Classifier: Operating System :: OS Independent
License-File: LICENSE_APACHE
